{
    "Autor": "", 
    "additional_info": "", 
    "aktualisiert": "Dienstag, 17. Dezember 2013 - 19:39", 
    "created": "Dienstag, 17. Dezember 2013 - 13:23", 
    "data_dictionary": "", 
    "description": "Einwohner mit Migrationshintergrund, aufgeteilt in Stadtteile, Stadtbezirke und die gesamte Stadt K\u00f6ln.\n\nHinweis zu Migrationshintergrund:\t\t\t\t\nDie Abgrenzung der Einwohner mit Migrationshintergrund wird durch Kombination verschiedener Merkmale aus dem Einwohnermeldeverfahren ermittelt. Die Angaben zum Umfang und zur Struktur sind daher im Gegensatz zu anderen Informationen zur Einwohnerstruktur, als Sch\u00e4tzwerte zu interpretieren, die Hinweise auf Gr\u00f6\u00dfenordnungen geben.\t\t\t\t\nDie Zahl der Einwohner mit Migrationshintergrund setzt sich aus folgenden Gruppen zusammen:\t\t\t\nDeutsche\t\t\t\t\t\nAussiedler\nDeutsche mit Herkunft aus ehemaligen Ostgebieten. Die Herkunft wird ermittelt anhand der 2. Nationalit\u00e4t oder des Geburtsortes (Geburtsdatum nach  08.05.1945) oder der Zuzugsherkunft (Zuzug nach 1968).\t\t\t\t\nEingeb\u00fcrgerte\nGeburtsort Ausland oder Einb\u00fcrgerungsurkunde\t\t\t\t\nKinder, Jugendliche und junge Erwachsene mit Option auf Einb\u00fcrgerung (Optionspflichtige) Unter 23 Jahre mit weiterer Staatsangeh\u00f6rigkeit. Gem. \u00a7\u00a7 4 (3), 40b, 29 (6) StAG.\t\t\t\nKinder und Jugendliche mit famili\u00e4rem Migrationshintergrund\t\t\t\t\nUnter 18 Jahre, alle Elternteile im Haushalt haben Migrationshintergrund\t\t\t\t\nNichtdeutsche\t\t\t\nAusl\u00e4nder/-innen der ersten Generation\nGeburtsort ist im Ausland\t\t\t\nAusl\u00e4nder/-innen \u00fcberwiegend zweite und dritte Generation\nGeburtsort ist in Deutschland\n\nQuelle: Stadt K\u00f6ln - Amt f\u00fcr Stadtentwicklung und Statistik (Statistisches Informationssystem)\n\n", 
    "frequency": "", 
    "granularity": "", 
    "id": "d39e54eb-fbc4-4ff2-95ca-558651073111", 
    "license": "Creative Commons Namensnennung 3.0 Deutschland Lizenz\r", 
    "publisher": "Stadt K\u00f6ln", 
    "resources": [
        {
            "created": "Dienstag, 17. Dezember 2013 - 13:34", 
            "description": "Einwohner nach Migrationshintergrund bezogen auf die Stadtteile der Stadt K\u00f6ln zum 31.12.2010", 
            "file_id": "ace848b7-36d9-42c3-961c-8739e6fc39ce", 
            "file_link": null, 
            "file_name": "2010_Migrationshintergrund_Stadtteil.csv", 
            "file_size": "3.14 KB", 
            "file_url": "http://offenedaten-koeln.de/sites/default/files/2010_Migrationshintergrund_Stadtteil.csv", 
            "format": "csv", 
            "id": "fb7d6ec4-df7a-47ca-bb7c-cd1a2e61d55d", 
            "link_to_api": null, 
            "mime_type": "text/csv", 
            "modified": "Dienstag, 17. Dezember 2013 - 13:34", 
            "title": "2010 Einwohner Migrationshintergrund Stadtteil", 
            "url": "/dataset/fb7d6ec4-df7a-47ca-bb7c-cd1a2e61d55d/resource/fb7d6ec4-df7a-47ca-bb7c-cd1a2e61d55d"
        }, 
        {
            "created": "Dienstag, 17. Dezember 2013 - 13:33", 
            "description": "Einwohner nach Migrationshintergrund bezogen auf die Stadtbezirke der Stadt K\u00f6ln zum 31.12.2010", 
            "file_id": "4a171501-dbf7-4776-9c93-bd5bcc9e30e2", 
            "file_link": null, 
            "file_name": "2010_Migrationshintergrund_Bezirk.csv", 
            "file_size": "573 Bytes", 
            "file_url": "http://offenedaten-koeln.de/sites/default/files/2010_Migrationshintergrund_Bezirk.csv", 
            "format": "csv", 
            "id": "afc4d9fd-c780-4170-a955-18fd05619447", 
            "link_to_api": null, 
            "mime_type": "text/csv", 
            "modified": "Dienstag, 17. Dezember 2013 - 13:33", 
            "title": "2010 Einwohner Migrationshintergrund Stadtbezirk", 
            "url": "/dataset/afc4d9fd-c780-4170-a955-18fd05619447/resource/afc4d9fd-c780-4170-a955-18fd05619447"
        }, 
        {
            "created": "Dienstag, 17. Dezember 2013 - 13:32", 
            "description": "Einwohner der Stadt K\u00f6ln nach Migrationshintergrund zum 31.12.2010", 
            "file_id": "81c86f39-4254-479e-82c6-9fced4f146fb", 
            "file_link": null, 
            "file_name": "2010_Migrationshintergrund_Insgesamt.csv", 
            "file_size": "309 Bytes", 
            "file_url": "http://offenedaten-koeln.de/sites/default/files/2010_Migrationshintergrund_Insgesamt.csv", 
            "format": "csv", 
            "id": "c958910a-8d05-4cb6-a228-e889421ef9f6", 
            "link_to_api": null, 
            "mime_type": "text/csv", 
            "modified": "Dienstag, 17. Dezember 2013 - 13:32", 
            "title": "2010 Einwohner Migrationshintergrund Insgesamt", 
            "url": "/dataset/c958910a-8d05-4cb6-a228-e889421ef9f6/resource/c958910a-8d05-4cb6-a228-e889421ef9f6"
        }, 
        {
            "created": "Dienstag, 17. Dezember 2013 - 13:31", 
            "description": "Einwohner nach Migrationshintergrund bezogen auf die Stadtteile der Stadt K\u00f6ln zum 31.12.2011\n", 
            "file_id": "4ff4e707-a6f0-4dc4-a260-bcc64db683d0", 
            "file_link": null, 
            "file_name": "2011_Migrationshintergrund_Stadtteil.csv", 
            "file_size": "3.14 KB", 
            "file_url": "http://offenedaten-koeln.de/sites/default/files/2011_Migrationshintergrund_Stadtteil.csv", 
            "format": "csv", 
            "id": "264ac177-2e82-4f25-80c2-7b6a2773fbad", 
            "link_to_api": null, 
            "mime_type": "text/csv", 
            "modified": "Dienstag, 17. Dezember 2013 - 13:31", 
            "title": "2011 Einwohner Migrationshintergrund Stadtteil", 
            "url": "/dataset/264ac177-2e82-4f25-80c2-7b6a2773fbad/resource/264ac177-2e82-4f25-80c2-7b6a2773fbad"
        }, 
        {
            "created": "Dienstag, 17. Dezember 2013 - 13:30", 
            "description": "Einwohner nach Migrationshintergrund bezogen auf die Stadtbezirke der Stadt K\u00f6ln zum 31.12.2011", 
            "file_id": "caca2998-eb9c-44bb-ac89-cc339fc7fb1a", 
            "file_link": null, 
            "file_name": "2011_Migrationshintergrund_Bezirk.csv", 
            "file_size": "573 Bytes", 
            "file_url": "http://offenedaten-koeln.de/sites/default/files/2011_Migrationshintergrund_Bezirk.csv", 
            "format": "csv", 
            "id": "ab41c82f-bef9-4dd2-bffd-d404f71ed196", 
            "link_to_api": null, 
            "mime_type": "text/csv", 
            "modified": "Dienstag, 17. Dezember 2013 - 13:30", 
            "title": "2011 Einwohner Migrationshintergrund Stadtbezirk", 
            "url": "/dataset/ab41c82f-bef9-4dd2-bffd-d404f71ed196/resource/ab41c82f-bef9-4dd2-bffd-d404f71ed196"
        }, 
        {
            "created": "Dienstag, 17. Dezember 2013 - 13:29", 
            "description": "Einwohner der Stadt K\u00f6ln nach Migrationshintergrund zum 31.12.2011", 
            "file_id": "28f3b16e-2be9-4a18-9a4c-0352ea261f52", 
            "file_link": null, 
            "file_name": "2011_Migrationshintergrund_Insgesamt.csv", 
            "file_size": "309 Bytes", 
            "file_url": "http://offenedaten-koeln.de/sites/default/files/2011_Migrationshintergrund_Insgesamt.csv", 
            "format": "csv", 
            "id": "a7b992ec-7ccb-4838-893a-c0563297af6e", 
            "link_to_api": null, 
            "mime_type": "text/csv", 
            "modified": "Dienstag, 17. Dezember 2013 - 13:29", 
            "title": "2011 Einwohner Migrationshintergrund Insgesamt", 
            "url": "/dataset/a7b992ec-7ccb-4838-893a-c0563297af6e/resource/a7b992ec-7ccb-4838-893a-c0563297af6e"
        }, 
        {
            "created": "Dienstag, 17. Dezember 2013 - 13:27", 
            "description": "Einwohner nach Migrationshintergrund bezogen auf die Stadtteile der Stadt K\u00f6ln zum 31.12.2012", 
            "file_id": "0f0040fe-e29e-4428-8250-aaee354e55c1", 
            "file_link": null, 
            "file_name": "2012_Migrationshintergrund_Stadtteil.csv", 
            "file_size": "2.97 KB", 
            "file_url": "http://offenedaten-koeln.de/sites/default/files/2012_Migrationshintergrund_Stadtteil.csv", 
            "format": "csv", 
            "id": "41ce89de-d3a4-4c47-8d99-4704afe483c9", 
            "link_to_api": null, 
            "mime_type": "text/csv", 
            "modified": "Dienstag, 17. Dezember 2013 - 13:27", 
            "title": "2012 Einwohner Migrationshintergrund Stadtteil", 
            "url": "/dataset/41ce89de-d3a4-4c47-8d99-4704afe483c9/resource/41ce89de-d3a4-4c47-8d99-4704afe483c9"
        }, 
        {
            "created": "Dienstag, 17. Dezember 2013 - 13:26", 
            "description": "Einwohner nach Migrationshintergrund bezogen auf die Stadtbezirke der Stadt K\u00f6ln zum 31.12.2012", 
            "file_id": "1d87a02e-0387-448a-9aa3-62dad424812a", 
            "file_link": null, 
            "file_name": "2012_Migrationshintergrund_Bezirk.csv", 
            "file_size": "573 Bytes", 
            "file_url": "http://offenedaten-koeln.de/sites/default/files/2012_Migrationshintergrund_Bezirk.csv", 
            "format": "csv", 
            "id": "594d1b99-3db7-46d3-9fb4-eee32a73b5a1", 
            "link_to_api": null, 
            "mime_type": "text/csv", 
            "modified": "Dienstag, 17. Dezember 2013 - 13:26", 
            "title": "2012 Einwohner Migrationshintergrund Stadtbezirk", 
            "url": "/dataset/594d1b99-3db7-46d3-9fb4-eee32a73b5a1/resource/594d1b99-3db7-46d3-9fb4-eee32a73b5a1"
        }, 
        {
            "created": "Dienstag, 17. Dezember 2013 - 13:25", 
            "description": "Einwohner der Stadt K\u00f6ln nach Migrationshintergrund zum 31.12.2012", 
            "file_id": "c8a2f871-5947-43d4-9c3c-53e178bb8c8f", 
            "file_link": null, 
            "file_name": "2012_Migrationshintergrund_Insgesamt.csv", 
            "file_size": "309 Bytes", 
            "file_url": "http://offenedaten-koeln.de/sites/default/files/2012_Migrationshintergrund_Insgesamt.csv", 
            "format": "csv", 
            "id": "437bd5fa-46fc-447e-89e8-c00512fdbab4", 
            "link_to_api": null, 
            "mime_type": "text/csv", 
            "modified": "Dienstag, 17. Dezember 2013 - 13:25", 
            "title": "2012 Einwohner Migrationshintergrund Insgesamt", 
            "url": "/dataset/437bd5fa-46fc-447e-89e8-c00512fdbab4/resource/437bd5fa-46fc-447e-89e8-c00512fdbab4"
        }
    ], 
    "spatial": "", 
    "tags": "Strukturdaten", 
    "temporal_coverage": "", 
    "title": "Einwohner mit MIgrationshintergrund"
}